sphinx_marimo/__init__.py
sphinx_marimo/builder.py
sphinx_marimo/directives.py
sphinx_marimo/extension.py
sphinx_marimo/py.typed
sphinx_marimo/static.py
sphinx_marimo/static/css/marimo-embed.css
sphinx_marimo/static/js/marimo-loader.js
sphinx_marimo-0.3.0.data/data/sphinx_marimo/static/css/marimo-embed.css
sphinx_marimo-0.3.0.data/data/sphinx_marimo/static/js/marimo-loader.js
sphinx_marimo-0.3.0.dist-info/METADATA
sphinx_marimo-0.3.0.dist-info/WHEEL
sphinx_marimo-0.3.0.dist-info/entry_points.txt
sphinx_marimo-0.3.0.dist-info/RECORD
