Metadata-Version: 2.4
Name: sphinx-marimo
Version: 0.3.0
Summary: Sphinx extension for embedding Marimo notebooks with WASM support
Author-email: koaning <vincentwarmerdam@gmail.com>
Requires-Python: >=3.10
Requires-Dist: joblib>=1.3.0
Requires-Dist: marimo>=0.1.0
Requires-Dist: pydata-sphinx-theme>=0.13.0
Requires-Dist: sphinx>=7.0.0
Provides-Extra: dev
Requires-Dist: mypy>=1.0.0; extra == 'dev'
Requires-Dist: pytest-cov>=4.0.0; extra == 'dev'
Requires-Dist: pytest>=7.0.0; extra == 'dev'
Requires-Dist: ruff>=0.1.0; extra == 'dev'
